r53_register/__init__.py
r53_register/cli.py
r53_register-0.1.7.dist-info/LICENSE
r53_register-0.1.7.dist-info/METADATA
r53_register-0.1.7.dist-info/WHEEL
r53_register-0.1.7.dist-info/entry_points.txt
r53_register-0.1.7.dist-info/top_level.txt
r53_register-0.1.7.dist-info/RECORD
