Metadata-Version: 2.1
Name: r53-register
Version: 0.1.7
Summary: Register your host IP address with Amazon Route 53.
Home-page: https://github.com/awkspace/r53-register
Author: awk
Author-email: awk@awk.space
License: MIT
Platform: UNKNOWN
Requires-Dist: boto3
Requires-Dist: dnspython
Requires-Dist: netifaces
Requires-Dist: requests
Provides-Extra: dev
Requires-Dist: twine ; extra == 'dev'
